{"name":"street-performer","album":"people","public_id":"people/street-performer","format":"tiff","version":1497005562,"created_at":"2017-06-09T10:52:42Z","width":964,"height":1440,"tags":[],"colors":[{"code":"#F19200","weight":46.1},{"code":"#2E1919","weight":10.7},{"code":"#E08C5F","weight":7.5},{"code":"#180605","weight":6.3},{"code":"#FDFBF9","weight":4.8},{"code":"#814E3A","weight":4.3},{"code":"#803C0D","weight":4},{"code":"#010004","weight":2.8},{"code":"#030004","weight":2.4},{"code":"#010101","weight":2},{"code":"#070106","weight":1.5},{"code":"#BB5C12","weight":1.5},{"code":"#130910","weight":1.4}]}